{
    "name": "Categorie",
    "fields": [
        {
            "fieldName": "section",
            "fieldType": "Section",
            "fieldValues": "U6,U7,U8,U9"
        },
        {
            "fieldName": "descrition",
            "fieldType": "String"
        }
    ],
    "relationships": [
        {
            "relationshipType": "many-to-one",
            "otherEntityName": "club",
            "otherEntityRelationshipName": "categorie",
            "relationshipName": "club",
            "otherEntityField": "id"
        },
        {
            "relationshipType": "many-to-one",
            "otherEntityName": "referent",
            "otherEntityRelationshipName": "categorie",
            "relationshipName": "referent",
            "otherEntityField": "id"
        }
    ],
    "changelogDate": "20200411230000",
    "entityTableName": "categorie",
    "dto": "no",
    "pagination": "no",
    "service": "no",
    "jpaMetamodelFiltering": false,
    "fluentMethods": true,
    "readOnly": false,
    "embedded": false,
    "clientRootFolder": "",
    "applications": "*"
}